{
  "id": "cosmology.mother_storm",
  "name": "Mother Storm",
  "truth_layer": "direct_canon",
  "summary": "A colossal east-polar whirlpool born from the compressed mass of a lost continent, defined by black glass crust, oceanic lensing, steam updrafts, thundercloud column, and smaller spin-off whirlpools.",
  "world_effects": [
    "treacherous sea travel",
    "global weather influence",
    "rare light-lensing phenomena at sunrise and sunset"
  ],
  "sources": [
    "pantheon_story",
    "ai_source_pdf",
    "spatial_seasonal"
  ]
}
