{
  "name": "House Mimolot",
  "type": "noble house faction",
  "truth_layer": "direct_canon",
  "summary": "Scholarly-magic house centered on education, book tariff systems, and controlled magical production.",
  "motive": "Maintain educational authority and magical legitimacy while controlling access to dangerous knowledge.",
  "methods": [
    "academy governance",
    "book tariffs",
    "artifact oversight",
    "research patronage"
  ],
  "geography": [
    "Mimolot Academy",
    "book production zones",
    "arcane facilities"
  ],
  "power_relations": [
    "Collaborates with Roaz and Union actors while guarding magical autonomy"
  ],
  "current_pressure": [
    "tariff resentment",
    "knowledge smuggling",
    "need to fund education without sparking rebellion"
  ],
  "visible_membership_base": "Scholars, instructors, archive clerks, licensed mages, artificers.",
  "civilian_contact_surface": [
    "tuition and book access",
    "artifact reviews",
    "licensing",
    "educational policy"
  ],
  "current_tension_or_vulnerability": "The house’s authority depends on knowledge control, so every leakage becomes both an economic and ideological wound.",
  "sources": [
    "principalities"
  ],
  "version": "V30_3",
  "generation_timestamp": "2026-04-18T03:13:23Z",
  "build_signature": "V30_3_REPOSITORY_HARDENING_AND_TRUTH_RESTORATION_RELEASE",
  "named_npc_refs": [
    "ithra_quillmark"
  ],
  "npc_interfaces": [
    "ithra_quillmark"
  ]
}
