{
  "name": "Emberforge Outpost",
  "inside": "Repair tools, barracks routines, patrol briefings, and shrine visits structure daily activity.",
  "truth_layer": "direct_canon",
  "hierarchy": {
    "polity": "Principality of Shelk",
    "territory": "House Shelk",
    "world": "Material Planet"
  },
  "interior_patterns": [
    "equipment repair is visibly part of daily life.",
    "Iron Beacon Shrine binds renewal and domination into road-protection symbolism.",
    "The difference between who belongs, who is tolerated, and who draws scrutiny becomes legible quickly once inside."
  ],
  "sources": [
    "locations_catalog"
  ]
}
