{
  "name": "The Tattered Banner",
  "parent_district": "Ironspool Ward District",
  "type": "tavern",
  "summary": "Meeting place for low-level sellswords.",
  "npc_interfaces": [
    "taren_stone",
    "lysa_stone"
  ],
  "truth_layer": "reconciled_canon",
  "sources": [
    "psc_shelkopolis",
    "locations_catalog"
  ],
  "named_npc_refs": [
    "taren_stone",
    "lysa_stone"
  ],
  "version": "V33_1",
  "generation_timestamp": "2026-04-19T02:36:22Z",
  "build_signature": "V33_1_WORLD_QA_CANON_SAFE_INTRO_AND_RUNTIME_SUPPORT_REBUILD"
}