{
  "build_version": "V33_1",
  "institution": "Eternal Lands armament lanes",
  "record_count": 1,
  "npc_ids": [
    "tharim_coalforge"
  ],
  "records": [
    {
      "npc_id": "tharim_coalforge",
      "canonical_name": "Tharim Coalforge",
      "polity": "Soreheim Alliance",
      "office_or_role": "Regional production boss",
      "tier": "grassroots",
      "public_reputation": "Known locally through day-to-day work as regional production boss.",
      "current_agenda": "Keep Ashforge Quarry workable through the obligations of regional production boss while managing the immediate pressure of predators in Soreheim Alliance."
    }
  ],
  "roster_context": {
    "identity": "Eternal Lands armament lanes is now linked to the strongest matching named NPC records available in-repository.",
    "visible_power": [],
    "pressure": []
  },
  "sources": [
    "repository_internal_reconciliation"
  ]
}
