{
  "name": "Hullwake Foundry",
  "type": "settlement",
  "hierarchy_parent": "House Cosmouth",
  "truth_layer": "source_backed_inference",
  "summary": "Storm-hardened floating fabrication quarter where emergency repair and naval improvisation define prestige.",
  "sources": [
    "V30_3 parity completion synthesis from polity summary and locality engine requirements."
  ],
  "named_npc_refs": [],
  "npc_interfaces": [
    "authority",
    "commerce",
    "faith or culture",
    "fixer",
    "wildcard"
  ],
  "version": "V30_3",
  "generation_timestamp": "2026-04-18T03:13:23Z",
  "build_signature": "V30_3_PARITY_COMPLETION_SUPPORT"
}
