{
  "name": "Duneshade Outpost",
  "parent_polity": "Soreheim Alliance",
  "type": "operational_anchor",
  "anchor_kind": "frontier_outpost",
  "truth_layer": "reconciled_canon",
  "anchor_status": "baseline_anchor",
  "roles_allocated": 6,
  "territory": "Eternal Lands",
  "operational_profile": "Hot-edge fortified node where route captains, rationing families, and predator-watch crews hold desertward lanes for the Unternal supply belt.",
  "role_density_note": "Emitted as matrix-stage administrative thickening rather than full office ledger.",
  "supporting_logic": "Built from existing polity logic as downward-and-outward operational fill.",
  "sources": [
    "soreheim_review",
    "spatial_seasonal"
  ]
}
